pytest_mocha/__init__.py
pytest_mocha/loader.py
pytest_mocha/plugin.py
pytest_mocha/reporter.py
pytest_mocha-0.4.0.dist-info/LICENSE.md
pytest_mocha-0.4.0.dist-info/METADATA
pytest_mocha-0.4.0.dist-info/WHEEL
pytest_mocha-0.4.0.dist-info/entry_points.txt
pytest_mocha-0.4.0.dist-info/top_level.txt
pytest_mocha-0.4.0.dist-info/RECORD
