Metadata-Version: 2.1
Name: pytest-mocha
Version: 0.4.0
Summary: pytest plugin to display test execution output like a mochajs
Home-page: https://github.com/rudineirk/pytest-mocha
Author: Rudinei Goi Roecker
Author-email: rudinei.roecker@gmail.com
License: MIT
Platform: UNKNOWN
Classifier: Development Status :: 4 - Beta
Classifier: Intended Audience :: Developers
Classifier: License :: OSI Approved :: MIT License
Classifier: Operating System :: OS Independent
Classifier: Programming Language :: Python
Classifier: Programming Language :: Python :: 3
Classifier: Programming Language :: Python :: 3.3
Classifier: Programming Language :: Python :: 3.4
Classifier: Programming Language :: Python :: 3.5
Classifier: Programming Language :: Python :: 3.6
Classifier: Programming Language :: Python :: 3.7
Classifier: Topic :: Software Development :: Testing
Classifier: Topic :: Software Development :: Libraries
Classifier: Topic :: Utilities
Requires-Dist: colorama (>=0.3.9)
Requires-Dist: pytest (>=5.4.0)
